replstories/__init__.py
replstories/mod.py
replstories-0.4.2.dist-info/LICENSE
replstories-0.4.2.dist-info/METADATA
replstories-0.4.2.dist-info/WHEEL
replstories-0.4.2.dist-info/top_level.txt
replstories-0.4.2.dist-info/RECORD
