Metadata-Version: 2.1
Name: replstories
Version: 0.4.2
Summary: Repl Stories is a social media platform where developers can share code and connect with the community!
Home-page: https://api.replstories.xyz/
Author: STGdevelopers
License: MIT
Platform: UNKNOWN
License-File: LICENSE
